omnigenbench/__init__.py
omnigenbench/auto/__init__.py
omnigenbench/auto/auto_bench/__init__.py
omnigenbench/auto/auto_bench/auto_bench.py
omnigenbench/auto/auto_bench/auto_bench_cli.py
omnigenbench/auto/auto_bench/config_check.py
omnigenbench/auto/auto_train/__init__.py
omnigenbench/auto/auto_train/auto_train.py
omnigenbench/auto/auto_train/auto_train_cli.py
omnigenbench/auto/bench_hub/__init__.py
omnigenbench/auto/bench_hub/bench_hub.py
omnigenbench/auto/config/__init__.py
omnigenbench/auto/config/auto_config.py
omnigenbench/cli/__init__.py
omnigenbench/cli/autoinfer_cli.py
omnigenbench/cli/ogb_cli.py
omnigenbench/cli/omnigenome_cli.py
omnigenbench/cli/commands/__init__.py
omnigenbench/cli/commands/base.py
omnigenbench/cli/commands/bench/__init__.py
omnigenbench/cli/commands/bench/bench_cli.py
omnigenbench/cli/commands/rna/__init__.py
omnigenbench/cli/commands/rna/rna_design.py
omnigenbench/src/__init__.py
omnigenbench/src/abc/__init__.py
omnigenbench/src/abc/abstract_dataset.py
omnigenbench/src/abc/abstract_explainer.py
omnigenbench/src/abc/abstract_metric.py
omnigenbench/src/abc/abstract_model.py
omnigenbench/src/abc/abstract_tokenizer.py
omnigenbench/src/abc/embedding_mixin.py
omnigenbench/src/dataset/__init__.py
omnigenbench/src/dataset/omni_dataset.py
omnigenbench/src/explainability/__init__.py
omnigenbench/src/explainability/attention/__init__.py
omnigenbench/src/explainability/attention/explainer.py
omnigenbench/src/explainability/epistasis/__init__.py
omnigenbench/src/explainability/epistasis/explainer.py
omnigenbench/src/explainability/sequence_logo/__init__.py
omnigenbench/src/explainability/sequence_logo/explainer.py
omnigenbench/src/explainability/shared_methods/__init__.py
omnigenbench/src/explainability/shared_methods/ism_explainer.py
omnigenbench/src/explainability/shared_methods/lime_explainer.py
omnigenbench/src/explainability/shared_methods/squid_explainer.py
omnigenbench/src/explainability/shared_methods/tsne_explainer.py
omnigenbench-0.4.2a0.dist-info/licenses/LICENSE
omnigenbench-0.4.2a0.dist-info/METADATA
omnigenbench-0.4.2a0.dist-info/WHEEL
omnigenbench-0.4.2a0.dist-info/entry_points.txt
omnigenbench-0.4.2a0.dist-info/top_level.txt
omnigenbench-0.4.2a0.dist-info/RECORD
