Metadata-Version: 2.4
Name: omnigenbench
Version: 0.4.2a0
Summary: OmniGenBench: A comprehensive toolkit for genome analysis benchmarking.
Home-page: https://github.com/yangheng95/OmniGenBench
Author: Yang, Heng
Author-email: hy345@exeter.ac.uk
License: Apache-2.0
Platform: Windows
Platform: Linux
Platform: Mac OS-X
Classifier: Development Status :: 3 - Alpha
Classifier: Intended Audience :: Science/Research
Classifier: License :: OSI Approved :: Apache Software License
Classifier: Programming Language :: Python :: 3.10
Classifier: Programming Language :: Python :: 3.11
Classifier: Programming Language :: Python :: 3.12
Classifier: Operating System :: OS Independent
Classifier: Topic :: Scientific/Engineering :: Bio-Informatics
Requires-Python: >=3.10
License-File: LICENSE
Requires-Dist: findfile>=2.0.0
Requires-Dist: autocuda>=0.16
Requires-Dist: metric-visualizer>=0.9.6
Requires-Dist: termcolor
Requires-Dist: gitpython
Requires-Dist: torch>=2.6.0
Requires-Dist: pandas
Requires-Dist: viennarna
Requires-Dist: scikit-learn
Requires-Dist: accelerate
Requires-Dist: transformers>=4.46.0
Requires-Dist: packaging
Requires-Dist: peft
Requires-Dist: dill
Requires-Dist: plotly
Requires-Dist: logomaker
Requires-Dist: matplotlib
Provides-Extra: dev
Requires-Dist: dill; extra == "dev"
Requires-Dist: pytest; extra == "dev"
Dynamic: author
Dynamic: author-email
Dynamic: classifier
Dynamic: description
Dynamic: description-content-type
Dynamic: home-page
Dynamic: license
Dynamic: license-file
Dynamic: platform
Dynamic: provides-extra
Dynamic: requires-dist
Dynamic: requires-python
Dynamic: summary
